iblai/__init__.py
iblai/api_client.py
iblai/api_response.py
iblai/clients.py
iblai/configuration.py
iblai/exceptions.py
iblai/py.typed
iblai/rest.py
iblai/api/__init__.py
iblai/api/ai_account_api.py
iblai/api/ai_analytics_api.py
iblai/api/ai_bot_api.py
iblai/api/ai_finetuning_api.py
iblai/api/ai_index_api.py
iblai/api/ai_marketing_api.py
iblai/api/ai_media_api.py
iblai/api/ai_mentor_api.py
iblai/api/ai_prompt_api.py
iblai/api/ai_search_api.py
iblai/api/analytics_api.py
iblai/api/career_api.py
iblai/api/catalog_api.py
iblai/api/commerce_api.py
iblai/api/core_api.py
iblai/api/credentials_api.py
iblai/api/custom_domains_api.py
iblai/api/features_api.py
iblai/api/media_api.py
iblai/api/notifications_api.py
iblai/api/recommendations_api.py
iblai/api/reports_api.py
iblai/api/scim_api.py
iblai/api/search_api.py
iblai/api/skills_api.py
iblai/helpers/__init__.py
iblai/helpers/constants.py
iblai/helpers/llm_credentials.py
iblai/helpers/mentor.py
iblai/helpers/mentor_async.py
iblai/helpers/user_invitation.py
iblai/models/__init__.py
iblai/models/acceptance_enum.py
iblai/models/access_enum.py
iblai/models/access_times_heatmap.py
iblai/models/accessible_mentors_by_email_request.py
iblai/models/accessible_mentors_by_email_response.py
iblai/models/action_breakdown.py
iblai/models/activate_user_free_trial.py
iblai/models/active_users_data.py
iblai/models/active_users_list.py
iblai/models/active_users_per_course.py
iblai/models/active_users_per_course_data.py
iblai/models/activity_api.py
iblai/models/activity_data.py
iblai/models/activity_info.py
iblai/models/add_mentor_to_disclaimer.py
iblai/models/ai_account_orgs_use_default_llm_key_create200_response.py
iblai/models/ai_account_orgs_users_free_trial_retrieve200_response.py
iblai/models/ai_generated_image.py
iblai/models/ai_user_profile_memory_relation.py
iblai/models/ai_user_profile_request.py
iblai/models/align_mentor_bubble_enum.py
iblai/models/analytics_overview.py
iblai/models/answer.py
iblai/models/app.py
iblai-4.89.4.dist-info/METADATA
iblai-4.89.4.dist-info/WHEEL
iblai-4.89.4.dist-info/top_level.txt
iblai-4.89.4.dist-info/RECORD
