Metadata-Version: 2.4
Name: iblai
Version: 4.89.4
Summary: ibl-data-manager
Home-page: https://github.com/iblai/iblai-python-sdk
Author: OpenAPI Generator community
Author-email: OpenAPI Generator Community <team@openapitools.org>
Project-URL: Repository, https://github.com/iblai/iblai-python-sdk
Keywords: OpenAPI,OpenAPI-Generator,ibl-data-manager
Requires-Python: >=3.9
Requires-Dist: urllib3<3.0.0,>=2.1.0
Requires-Dist: python-dateutil>=2.8.2
Requires-Dist: pydantic>=2
Requires-Dist: typing-extensions>=4.7.1
Dynamic: author
Dynamic: home-page
